dav_utils/__init__.py
dav_utils/config.py
dav_utils/descriptors.py
dav_utils/logger.py
dav_utils/utils.py
dav_utils-0.2.5.dist-info/LICENSE
dav_utils-0.2.5.dist-info/METADATA
dav_utils-0.2.5.dist-info/WHEEL
dav_utils-0.2.5.dist-info/top_level.txt
dav_utils-0.2.5.dist-info/RECORD
