Metadata-Version: 2.1
Name: dav-utils
Version: 0.2.5
Summary: Set of tools that often have to reproduce in Python scripts
Home-page: https://github.com/devalv/utils
Author: Aleksey Devyatkin
Author-email: devyatkin.av@ya.ru
License: UNKNOWN
Platform: UNKNOWN
Classifier: Programming Language :: Python :: 3
Classifier: License :: OSI Approved :: MIT License
Classifier: Operating System :: OS Independent
Requires-Python: >=3.5
